ordlookup-stubs/__init__.pyi
ordlookup-stubs/oleaut32.pyi
ordlookup-stubs/py.typed
ordlookup-stubs/ws2_32.pyi
ordlookup-stubs/_generated/oleaut32.pyi
ordlookup-stubs/_generated/ws2_32.pyi
pefile-stubs/__init__.pyi
pefile-stubs/py.typed
pefile-stubs/_generated/pefile_formats.pyi
pefile-stubs/_generated/pefile_lookup.pyi
types_pefile-2023.2.7.post0.dist-info/COPYING
types_pefile-2023.2.7.post0.dist-info/LICENSE
types_pefile-2023.2.7.post0.dist-info/LICENSE.pefile
types_pefile-2023.2.7.post0.dist-info/METADATA
types_pefile-2023.2.7.post0.dist-info/WHEEL
types_pefile-2023.2.7.post0.dist-info/top_level.txt
types_pefile-2023.2.7.post0.dist-info/RECORD
