Metadata-Version: 2.1
Name: types-pefile
Version: 2023.2.7.post0
Summary: Type stubs for pefile.
Author-email: ColoursOfNoise <coloursofthenoise@gmail.com>
License: GPLv3+
Project-URL: Homepage, https://github.com/coloursofnoise/types-pefile
Keywords: pefile,stubs,typing
Classifier: Intended Audience :: Developers
Classifier: License :: OSI Approved :: GNU General Public License v3 or later (GPLv3+)
Classifier: Operating System :: OS Independent
Classifier: Programming Language :: Python :: 3
Classifier: Typing :: Stubs Only
License-File: LICENSE
License-File: LICENSE.pefile
License-File: COPYING
Requires-Dist: pefile (~=2023.2.7)
